convert/extractor.py
convert/hyper_reader.py
convert/path_types.py
convert/table_types.py
convert/tdsx.py
convert/writers.py
simtab-0.1.1.dist-info/METADATA
simtab-0.1.1.dist-info/WHEEL
simtab-0.1.1.dist-info/top_level.txt
simtab-0.1.1.dist-info/RECORD
